spikelearn/__init__.py
spikelearn/generators.py
spikelearn/layer.py
spikelearn/loihi.py
spikelearn/neurons.py
spikelearn/rules.py
spikelearn/snn.py
spikelearn/synapses.py
spikelearn/ternary.py
spikelearn/trace.py
spikelearn/transforms.py
spikelearn/streamnet/__init__.py
spikelearn/streamnet/element.py
spikelearn/streamnet/io.py
spikelearn/streamnet/streamnet.py
spikelearn-0.1.2.dist-info/LICENSE.md
spikelearn-0.1.2.dist-info/METADATA
spikelearn-0.1.2.dist-info/WHEEL
spikelearn-0.1.2.dist-info/top_level.txt
spikelearn-0.1.2.dist-info/RECORD
