Metadata-Version: 2.1
Name: spikelearn
Version: 0.1.2
Summary: Spiking neural networks for AI workflows and neuromorphic computing
Author: Angel Yanguas-Gil
Project-URL: Homepage, https://github.com/spikelearn/spikelearn
Keywords: spiking neurons,neural networks,AI,neuromorphic computing,spiking neural networks,neuroscience
Classifier: Programming Language :: Python :: 3
Classifier: License :: OSI Approved :: BSD License
Classifier: Operating System :: OS Independent
License-File: LICENSE.md
Requires-Dist: numpy
